crowdsource/__init__.py
crowdsource/basisspline.py
crowdsource/crowdsource_base.py
crowdsource/decam_inject.py
crowdsource/decam_proc.py
crowdsource/deconv_psf.py
crowdsource/galaxy_mask.py
crowdsource/galconv.py
crowdsource/mosaic.py
crowdsource/nebulosity_mask.py
crowdsource/psf.py
crowdsource/simple_proc.py
crowdsource/unwise_primary.py
crowdsource/wise_proc.py
crowdsourcephoto-0.5.9.dist-info/LICENSE
crowdsourcephoto-0.5.9.dist-info/METADATA
crowdsourcephoto-0.5.9.dist-info/WHEEL
crowdsourcephoto-0.5.9.dist-info/top_level.txt
crowdsourcephoto-0.5.9.dist-info/RECORD
